{
  "source": "namu.wiki",
  "source_url": "https://namu.wiki/w/%EC%84%B1%EA%B8%B0%ED%95%99",
  "resolved_title": "성기학",
  "attempted_titles": [
    "성기학"
  ],
  "position": "영원무역 그룹 초대 회장",
  "name_ko": "성기학",
  "name_hanja": "",
  "name_en": "",
  "profile_image": "https://i.namu.wiki/i/1QmbddP1tt7KLIa1528sfkw2ZdjYqrEBZ4n50qXHOCd5kkHuSyZR8aRamPK-5CtwfI-IwdUuiom6JgG9fcpK8fWQO-bexQyaz0j-9YQChT94T9kh5fSIosvmXzNn5zBAm7SRKzoPWTvVu2uOk92mXw.webp",
  "birth_date": "1947년 7월 8일",
  "family": {
    "parents": {
      "father": {
        "name": "",
        "url": ""
      },
      "mother": {
        "name": "",
        "url": ""
      }
    },
    "siblings": {
      "형": [],
      "누나": [],
      "오빠": [],
      "언니": [],
      "동생": [],
      "미분류": []
    },
    "spouse": [],
    "children": [],
    "flatten": {}
  }
}